docs/Makefile
docs/make.bat
docs/source/conf.py
docs/source/index.rst
docs/source/modules.rst
docs/source/torch_ransac3d.rst
docs/source/_static/logo.png
images/logo.png
images/logo.svg
tests/*
tests/conftest.py
tests/test_cuboid.py
tests/test_line.py
tests/test_plane.py
tests/test_point.py
tests/test_sphere.py
tests/view_line_fit.py
tests/view_plane_fit.py
tests/view_sphere_fit.py
torch_ransac3d/__init__.py
torch_ransac3d/_version.py
torch_ransac3d/cuboid.py
torch_ransac3d/dataclasses.py
torch_ransac3d/line.py
torch_ransac3d/plane.py
torch_ransac3d/point.py
torch_ransac3d/sphere.py
torch_ransac3d/util.py
torch_ransac3d/wrapper.py
torch_ransac3d-2.0.0.dist-info/LICENSE
torch_ransac3d-2.0.0.dist-info/METADATA
torch_ransac3d-2.0.0.dist-info/WHEEL
torch_ransac3d-2.0.0.dist-info/top_level.txt
torch_ransac3d-2.0.0.dist-info/RECORD
