Metadata-Version: 2.2
Name: torch_ransac3d
Version: 2.0.0
Summary: A high-performance implementation of 3D RANSAC (Random Sample Consensus) algorithm using PyTorch and CUDA.
Author-email: Harry Dobbs <harrydobbs87@gmail.com>
License: MIT
Project-URL: Homepage, https://github.com/harrydobbs/torch_ransac3d
Project-URL: Documentation, https://harrydobbs.github.io/torch_ransac3d/
Project-URL: Issues, https://github.com/harrydobbs/torch_ransac3d/issues
Requires-Python: >=3.8
License-File: LICENSE
Requires-Dist: numpy
Requires-Dist: torch
Provides-Extra: dev
Requires-Dist: sphinx; extra == "dev"
Requires-Dist: sphinx-autodoc-typehints; extra == "dev"
Requires-Dist: sphinx-rtd-theme; extra == "dev"
Requires-Dist: pytest; extra == "dev"
Requires-Dist: pytest-cov; extra == "dev"
Requires-Dist: pytest-xdist; extra == "dev"
Requires-Dist: pytest-timeout; extra == "dev"
